hanbert_tokenizer/__init__.py
hanbert_tokenizer/tokenization_hanbert.py
hanbert_tokenizer/moran/__init__.py
hanbert_tokenizer/moran/config.json
hanbert_tokenizer/moran/libmoran4dnlp.so
hanbert_tokenizer/moran/udict.txt
hanbert_tokenizer/moran/uentity.txt
hanbert_tokenizer/moran/vocab_54k.txt
hanbert_tokenizer-0.1.7.dist-info/METADATA
hanbert_tokenizer-0.1.7.dist-info/WHEEL
hanbert_tokenizer-0.1.7.dist-info/top_level.txt
hanbert_tokenizer-0.1.7.dist-info/RECORD
