Metadata-Version: 2.1
Name: hanbert-tokenizer
Version: 0.1.7
Summary: Hanbert Tokenizer
Home-page: https://github.com/tbai2019/HanBARTT
Author: TwoBlockAI
Author-email: indexxlim@gmail.com
License: UNKNOWN
Keywords: hanbert,tokenizer,moran
Platform: UNKNOWN
Requires-Python: >=3
Requires-Dist: torch (>=1.7.1)
Requires-Dist: transformers (>=4.3.3)
